pmemstat/CpuSmooth.py
pmemstat/KillThem.py
pmemstat/__init__.py
pmemstat/main.py
pmemstat-3.0.6.dist-info/entry_points.txt
pmemstat-3.0.6.dist-info/licenses/LICENSE.txt
pmemstat-3.0.6.dist-info/WHEEL
pmemstat-3.0.6.dist-info/METADATA
pmemstat-3.0.6.dist-info/RECORD
