Metadata-Version: 2.4
Name: pmemstat
Version: 3.0.6
Summary: Report Proportional Memory on Linux
Keywords: proportional memory,RAM,htop,top,monitor
Author-email: Joe Defen <joedef@duck.com>
Requires-Python: >=3.8
Classifier: Programming Language :: Python :: 3
Classifier: License :: OSI Approved :: MIT License
Classifier: Operating System :: POSIX :: Linux
License-File: LICENSE.txt
Requires-Dist: psutil > 5.9
Requires-Dist: console-window == 1.3.2
Project-URL: Bug Tracker, https://github.com/joedefen/pmemstat/issues
Project-URL: Homepage, https://github.com/joedefen/pmemstat
